proctor/__init__.py
proctor/_core.py
proctor/py.typed
bolton_proctor-0.2.2.dist-info/METADATA
bolton_proctor-0.2.2.dist-info/WHEEL
bolton_proctor-0.2.2.dist-info/top_level.txt
bolton_proctor-0.2.2.dist-info/RECORD
